nr/__init__.py
nr/ansiterm.py
nr.ansiterm-0.0.2.dist-info/LICENSE.txt
nr.ansiterm-0.0.2.dist-info/METADATA
nr.ansiterm-0.0.2.dist-info/WHEEL
nr.ansiterm-0.0.2.dist-info/top_level.txt
nr.ansiterm-0.0.2.dist-info/zip-safe
nr.ansiterm-0.0.2.dist-info/RECORD
