Metadata-Version: 2.1
Name: nr.ansiterm
Version: 0.0.2
Summary: Package description here.
Home-page: https://git.niklasrosenstein.com/NiklasRosenstein/nr
Author: Niklas Rosenstein
Author-email: rosensteinniklas@gmail.com
License: MIT
Platform: UNKNOWN
Requires-Python: >=3.5.0,<4.0.0
Requires-Dist: nr.pylang.utils (<0.1.0,>=0.0.2)
